LICENSE
MANIFEST.in
README.md
requirements.txt
setup.cfg
setup.py
src/os_sanic/VERSION
src/os_sanic/__init__.py
src/os_sanic/application.py
src/os_sanic/blueprint.py
src/os_sanic/cmdline.py
src/os_sanic/config.py
src/os_sanic/extension.py
src/os_sanic/log.py
src/os_sanic/manage.py
src/os_sanic/monkey_patch.py
src/os_sanic/prototype.py
src/os_sanic/server.py
src/os_sanic/utils.py
src/os_sanic.egg-info/PKG-INFO
src/os_sanic.egg-info/SOURCES.txt
src/os_sanic.egg-info/dependency_links.txt
src/os_sanic.egg-info/entry_points.txt
src/os_sanic.egg-info/not-zip-safe
src/os_sanic.egg-info/requires.txt
src/os_sanic.egg-info/top_level.txt
src/os_sanic/commands/__init__.py
src/os_sanic/commands/global/__init__.py
src/os_sanic/commands/global/startproject.py
src/os_sanic/commands/project/__init__.py
src/os_sanic/commands/project/info.py
src/os_sanic/commands/project/run.py
src/os_sanic/commands/project/startapp.py
src/os_sanic/commands/template/app_template/__init__.py-tpl
src/os_sanic/commands/template/app_template/app.py-tpl
src/os_sanic/commands/template/app_template/error_handler.py-tpl
src/os_sanic/commands/template/app_template/extension.py-tpl
src/os_sanic/commands/template/app_template/handler.py-tpl
src/os_sanic/commands/template/app_template/middleware.py-tpl
src/os_sanic/commands/template/app_template/static/README.txt-tpl
src/os_sanic/commands/template/apps_template/__init__.py-tpl
src/os_sanic/commands/template/project_template/config.py-tpl
src/os_sanic/commands/template/project_template/manage.py-tpl
tests/__init__.py
tests/cmd_runner.py
tests/conftest.py
tests/manage_for_test.py
tests/test_cmdline.py
tests/test_utils.py
tests/test_view.py
tests/utils.py
tests/apps/__init__.py
tests/apps/case01/__init__.py
tests/apps/case01/app.py
tests/apps/case01/extension.py
tests/apps/case01/view.py
tests/apps/case02/__init__.py
tests/apps/case02/app.py
tests/apps/case02/extension.py
tests/apps/case02/view.py
tests/apps/case02/static/hello.txt