Metadata-Version: 2.1
Name: os-sanic
Version: 0.1.7
Summary: A framework to simplify Sanic daemon development.
Home-page: https://github.com/cfhamlet/os-sanic
Author: Ozzy
Author-email: cfhamlet@gmail.com
License: MIT License
Platform: UNKNOWN
Classifier: Development Status :: 2 - Pre-Alpha
Classifier: Intended Audience :: Developers
Classifier: License :: OSI Approved :: MIT License
Classifier: Natural Language :: English
Classifier: Programming Language :: Python :: 3
Classifier: Programming Language :: Python :: 3.6
Classifier: Programming Language :: Python :: Implementation :: CPython
Requires-Python: >=3.6
Provides-Extra: openapi
